unu_api/__init__.py
unu_api/api.py
unu_api/client.py
unu_api/exceptions.py
unu_api-0.2.4.dist-info/WHEEL
unu_api-0.2.4.dist-info/METADATA
unu_api-0.2.4.dist-info/RECORD
