Metadata-Version: 2.1
Name: unu-api
Version: 0.2.4
Summary: Библиотека для интеграции с биржой микрозадач unu.im
Home-page: https://egorovegor.ru
Author: Egorov Egor
Requires-Python: >=3.5,<4.0
Classifier: Programming Language :: Python :: 3
Classifier: Programming Language :: Python :: 3.10
Classifier: Programming Language :: Python :: 3.5
Classifier: Programming Language :: Python :: 3.6
Classifier: Programming Language :: Python :: 3.7
Classifier: Programming Language :: Python :: 3.8
Classifier: Programming Language :: Python :: 3.9
Requires-Dist: requests (>=2.26.0,<3.0.0)
Project-URL: Repository, https://github.com/r4hx/unu_api/
